glpy/__init__.py
glpy/main.py
glpy/utils.py
glpy-0.1.1.dist-info/LICENSE
glpy-0.1.1.dist-info/METADATA
glpy-0.1.1.dist-info/WHEEL
glpy-0.1.1.dist-info/top_level.txt
glpy-0.1.1.dist-info/RECORD
