Metadata-Version: 2.1
Name: glpy
Version: 0.1.1
Summary: An pyOpneGL Wrapper
Home-page: https://github.com/abhinav-TB/glpy
Author: Abhinav TB
Author-email: abhinavtb@gmail.com
License: Apache License 2.0
Platform: UNKNOWN
